chiss/__init__.py
chiss/daskill.py
chiss/rat.py
chiss-1.0.4.dist-info/LICENSE
chiss-1.0.4.dist-info/METADATA
chiss-1.0.4.dist-info/WHEEL
chiss-1.0.4.dist-info/top_level.txt
chiss-1.0.4.dist-info/RECORD
