Metadata-Version: 2.1
Name: chiss
Version: 1.0.4
Summary: Le package des rats
Home-page: https://github.com/Jachou-yt/chissProject
Author: Jachou
Author-email: matisse.martayan@gmail.com
Project-URL: Bug Tracker, https://github.com/Jachou-yt/chissProject/issues
Classifier: Programming Language :: Python :: 3
Classifier: License :: OSI Approved :: MIT License
Classifier: Operating System :: OS Independent
Requires-Python: >=3.6
License-File: LICENSE
